jsondispatch
jsondispatch/trigger_commands
