Metadata-Version: 2.1
Name: jsondispatch
Version: 0.1.4
Summary: Dispatch commands with JSON HTTP requests
Home-page: https://github.com/ibizaman/jsondispatch
Author: Pierre Penninckx
Author-email: ibizapeanut@gmail.com
License: GPLv3
Download-URL: https://github.com/ibizaman/jsondispatch/archive/0.1.4.tar.gz
Keywords: json,aiohttp
Platform: UNKNOWN
Provides-Extra: dev
Provides-Extra: test
